{
  "custom_rules_version": "1.0",
  "last_updated": "2025-11-23T21:40:00Z",
  "rules": {},
  "rule_count": 0,
  "active_rules": 0,
  "disabled_rules": 0,
  "examples": {
    "example_file_limit": {
      "description": "Example: Limit Python files to 200 lines",
      "user_statement": "All Python files should be limited to 200 lines instead of 250",
      "parsed_rule": {
        "category": "file_limits",
        "parameters": {
          "file_type": "py",
          "line_limit": 200,
          "scope": "all_repositories"
        }
      }
    },
    "example_workflow": {
      "description": "Example: Require code review for large files",
      "user_statement": "Add a rule that requires code review for any file over 100 lines",
      "parsed_rule": {
        "category": "workflow_requirements",
        "parameters": {
          "trigger_condition": "file_size > 100",
          "required_action": "code_review",
          "scope": "all_files"
        }
      }
    }
  }
}
